README.rst
setup.py
Flask_Thunderargs.egg-info/PKG-INFO
Flask_Thunderargs.egg-info/SOURCES.txt
Flask_Thunderargs.egg-info/dependency_links.txt
Flask_Thunderargs.egg-info/requires.txt
Flask_Thunderargs.egg-info/top_level.txt
flask_thunderargs/__init__.py