Metadata-Version: 1.0
Name: Flask-Thunderargs
Version: 0.3
Summary: Implements thunderargs to flask framework.
Home-page: https://bitbucket.org/dsupiev/flask-thunderargs
Author: uthunderbird
Author-email: undead.thunderbird@gmail.com
License: JSON license
Platform: UNKNOWN
